{"sections":{"c32995d4-3d31-4552-9fdb-21735e8929dd":{"type":"hunza-hero","blocks":{"5e5d0ba1-b3c4-41a2-b66b-919e2450c80e":{"type":"icon","settings":{"icon_image":"shopify:\/\/shop_images\/rose_logo_2x_27cd3cbc-f8bb-4d97-857b-21c2ae1401f0.png"}},"4d457222-c4c2-40f3-aad7-b1c5d5806c0a":{"type":"icon","settings":{"icon_image":"shopify:\/\/shop_images\/hunza_logo_2x_39571f6c-6ef4-4902-b3e3-337b58bbe66d.png"}}},"block_order":["5e5d0ba1-b3c4-41a2-b66b-919e2450c80e","4d457222-c4c2-40f3-aad7-b1c5d5806c0a"],"settings":{"hero_title_desk":"The Solar Effect","hero_description_desk":"<p>A new wave of summer style featuring the Solar Collection <br\/>and Hunza G's signature swimsuits.<\/p>","text_margin_top_desk":"-81px","desktop_image":"shopify:\/\/shop_images\/hunza_hero_desktop_2x_7af4fbb8-e44f-4296-a7b3-5c76ba97dbef.jpg","desktop_video_url":"","custom_desktop_video_url":"https:\/\/cdn.shopify.com\/videos\/c\/o\/v\/619cd41f264d43a59de478a8b7f0dda4.mp4","custom_desktop_video_description":"","hero_title_mob":"The Solar Effect","hero_description_mob":"<p>Our Solar Collection and iconic <br\/>crinkle swimsuit by Hunza come <br\/>together to spark your summer style.<\/p>","text_margin_top_mob":"-29px","mobile_image":"shopify:\/\/shop_images\/hunza_hero_mobile_2x_1c6a0f0d-a650-44eb-8e7f-b1608c2e1ebd.jpg","mobile_video_url":"","custom_mobile_video_url":"https:\/\/cdn.shopify.com\/videos\/c\/o\/v\/eaada57cf0e745dca5a4503b3cf33331.mp4","custom_mobile_video_description":"","gnav_color":"light"}},"0424b625-9c85-4049-ab1b-65afb44663b3":{"type":"hotspots-double-img","blocks":{"88f59d69-c9f3-4344-9fc0-560e0b07a532":{"type":"slide","settings":{"double_prod":"lip-treatment-hydrating-lip-balm","double_prod_variant":"42523138916540","extra_text":"","position_vertical":55,"position_horizontal":43}},"dd993a70-37b3-41de-b14d-b6754a4ed75e":{"type":"slide","settings":{"double_prod":"solar-power-luminous-spf-30-serum","double_prod_variant":"41516862701756","extra_text":"","position_vertical":36,"position_horizontal":29}},"f7bc7b5a-1292-4a6f-9a18-bdb17f39acda":{"type":"slide","settings":{"double_prod":"skin-enhance-luminous-tinted-serum","double_prod_variant":"","extra_text":"Anna wears shade 060","position_vertical":69,"position_horizontal":24}}},"block_order":["88f59d69-c9f3-4344-9fc0-560e0b07a532","dd993a70-37b3-41de-b14d-b6754a4ed75e","f7bc7b5a-1292-4a6f-9a18-bdb17f39acda"],"settings":{"double_background":"#ffffff","big_left_small_right":false,"big_bottom_small_top":false,"small_image":"shopify:\/\/shop_images\/img.jpg","video_url":"","custom_video_url":"https:\/\/cdn.shopify.com\/videos\/c\/o\/v\/b312ac292c174698bd9e4faf66393a37.mp4","custom_video_alt":"","enable_video_control":true,"controle_alignment":"left","big_image":"shopify:\/\/shop_images\/hunza-img-2.jpg"}},"da2b51aa-4563-4421-9406-c8daa7abaa7d":{"type":"centered-title","settings":{"centered_background":"#ffffff","centered_title":"A lifestyle inspired by paradise — wherever you are."}},"feb2a2b7-8f1a-4d41-ae0b-17d2d798585e":{"type":"hotspots-double-img","blocks":{"d315588b-ae51-47e4-9ad9-35f5d9dce914":{"type":"slide","settings":{"double_prod":"satin-shimmer-duet-eyeshadow","double_prod_variant":"41856703791292","extra_text":"Lindsey wears Olive & Khaki Shimmer","position_vertical":32,"position_horizontal":58}},"66271a69-b7d8-4fa8-8d0f-0dfc93b541b2":{"type":"slide","settings":{"double_prod":"lip-cream-weightless-matte-color","double_prod_variant":"42531185787068","extra_text":"Lindsey wears shade Love Beckons","position_vertical":65,"position_horizontal":78}},"77970334-1810-40d0-8189-ce02f044f886":{"type":"slide","settings":{"double_prod":"solar-infusion-soft-focus-cream-bronzer","double_prod_variant":"41658098450620","extra_text":"Lindsey wears shade Seychelles","position_vertical":45,"position_horizontal":38}}},"block_order":["d315588b-ae51-47e4-9ad9-35f5d9dce914","66271a69-b7d8-4fa8-8d0f-0dfc93b541b2","77970334-1810-40d0-8189-ce02f044f886"],"settings":{"double_background":"#ffffff","big_left_small_right":true,"big_bottom_small_top":false,"video_url":"","custom_video_url":"https:\/\/cdn.shopify.com\/videos\/c\/o\/v\/e40907c0a57045bca3b341d57fe28a43.mp4","custom_video_alt":"","enable_video_control":true,"controle_alignment":"right","big_image":"shopify:\/\/shop_images\/hunza-img-3.jpg"}},"533416d8-c9d2-45ca-b5cf-fa88ad919946":{"type":"hotspots-prodts-img-split","blocks":{"1d02fcaf-c458-4ab8-b23b-87c06e1cccc2":{"type":"slide","settings":{"split_prod":"solar-radiance-hydrating-cream-highlighter","split_prod_variant":"41658033635516","extra_text":"Lindsey wears shade Lustrous","split_vertical":39,"split_horizontal":61}},"7c4bd0db-a248-4d9e-a68c-b040a9422c98":{"type":"slide","settings":{"split_prod":"cream-blush","split_prod_variant":"","extra_text":"Lindsey wears shade Hibiscus","split_vertical":49,"split_horizontal":67}},"16a69029-4494-4020-99a0-fc9dfa792e6d":{"type":"slide","settings":{"split_prod":"solar-infusion-soft-focus-cream-bronzer","split_prod_variant":"41658098450620","extra_text":"Lindsey wears shade Seychelles","split_vertical":30,"split_horizontal":74}}},"block_order":["1d02fcaf-c458-4ab8-b23b-87c06e1cccc2","7c4bd0db-a248-4d9e-a68c-b040a9422c98","16a69029-4494-4020-99a0-fc9dfa792e6d"],"settings":{"image_left_prod_right":false,"split_background":"#fafafa","split_title":"Sunrise Radiance","split_description":"<p>Soft copper tones that add gentle warmth.<\/p>","split_image":"shopify:\/\/shop_images\/hunza-img-5.jpg"}},"64659452-7388-451e-acff-8fb761f6df85":{"type":"hotspots-double-img","blocks":{"67938183-2fec-402b-bfc8-bc2a8f6121cd":{"type":"slide","settings":{"double_prod":"skin-enhance-luminous-tinted-serum","double_prod_variant":"","extra_text":"","position_vertical":29,"position_horizontal":71}},"296dd870-0664-41bc-8659-c02a3ecc31e9":{"type":"slide","settings":{"double_prod":"solar-power-luminous-spf-30-serum","double_prod_variant":"41516862701756","extra_text":"","position_vertical":56,"position_horizontal":26}}},"block_order":["67938183-2fec-402b-bfc8-bc2a8f6121cd","296dd870-0664-41bc-8659-c02a3ecc31e9"],"settings":{"double_background":"#ffffff","big_left_small_right":false,"big_bottom_small_top":true,"small_image":"shopify:\/\/shop_images\/hunza-img-6.jpg","video_url":"","custom_video_url":"","custom_video_alt":"","enable_video_control":false,"controle_alignment":"right","big_image":"shopify:\/\/shop_images\/hunza-img-7.jpg"}},"6ab41c6c-7119-447f-bfcc-1aa1e0a8aecf":{"type":"centered-title","settings":{"centered_background":"#ffffff","centered_title":"Luminous looks capturing the essence of tropical sun."}},"9861a174-b773-479a-8ba1-fbc9894c04e3":{"type":"hotspots-double-img","blocks":{"ca261b8d-1069-46c7-b464-87835189e921":{"type":"slide","settings":{"double_prod":"solar-radiance-hydrating-cream-highlighter","double_prod_variant":"41658033635516","extra_text":"Anna wears shade Lustrous","position_vertical":59,"position_horizontal":21}},"d22d6e77-7100-4a2e-b7a3-89c383d9903d":{"type":"slide","settings":{"double_prod":"cream-blush","double_prod_variant":"40549025611964","extra_text":"Anna wears shade Ophelia","position_vertical":38,"position_horizontal":72}},"001b6a20-983a-49ac-adbc-81268fc53678":{"type":"slide","settings":{"double_prod":"lip-cream-weightless-matte-color","double_prod_variant":"42531185688764","extra_text":"Anna wears shade Of Stars","position_vertical":65,"position_horizontal":39}}},"block_order":["ca261b8d-1069-46c7-b464-87835189e921","d22d6e77-7100-4a2e-b7a3-89c383d9903d","001b6a20-983a-49ac-adbc-81268fc53678"],"settings":{"double_background":"#ffffff","big_left_small_right":true,"big_bottom_small_top":false,"video_url":"","custom_video_url":"https:\/\/cdn.shopify.com\/videos\/c\/o\/v\/ddd028379d7e42e9a1c8a9ddb3ea205b.mp4","custom_video_alt":"","enable_video_control":true,"controle_alignment":"right","big_image":"shopify:\/\/shop_images\/hunza-img-8_8713bb49-debf-4ac4-9eaa-25b3def654ff.jpg"}},"d3f799f6-fd0d-4f02-8fb2-5534699e21c8":{"type":"hotspots-prodts-img-split","blocks":{"bfd1e4f8-44d6-4c53-8c7a-565e5db99988":{"type":"slide","settings":{"split_prod":"solar-infusion-soft-focus-cream-bronzer","split_prod_variant":"41658098385084","extra_text":"Anna wears shade Parrot Cay","split_vertical":45,"split_horizontal":13}},"34353b48-4c0f-42d3-b43a-ee031208a4e1":{"type":"slide","settings":{"split_prod":"satin-shimmer-duet-eyeshadow","split_prod_variant":"","extra_text":"Anna wears shade Cocoa & White Gold Shimmer","split_vertical":20,"split_horizontal":23}},"eec83839-7738-417b-858e-cdeb946dd083":{"type":"slide","settings":{"split_prod":"lip-cream-weightless-matte-color","split_prod_variant":"42531185918140","extra_text":"Anna wears shade Mortal Flame","split_vertical":65,"split_horizontal":55}}},"block_order":["bfd1e4f8-44d6-4c53-8c7a-565e5db99988","34353b48-4c0f-42d3-b43a-ee031208a4e1","eec83839-7738-417b-858e-cdeb946dd083"],"settings":{"image_left_prod_right":true,"split_background":"#fafafa","split_title":"Golden Hour Glow","split_description":"<p>Sultry, sun-kissed hues to look lit from within.<\/p>","split_image":"shopify:\/\/shop_images\/hunza-img-10.jpg"}},"7056d813-74f7-4095-865b-047883a75cf0":{"type":"hunza-about-top","settings":{"about_title":"About the Partnership","about_description":"<p>In 2019, Rosie Huntington-Whiteley posted photos of herself wearing <a href=\"https:\/\/www.hunzag.com\/\" target=\"_blank\" title=\"Hunza G\"><span style=\"text-decoration:underline\">Hunza G<\/span>’<\/a>s iconic Domino Blush while on holiday, redefining it as the swimsuit that broke the internet. With a shared value for elevated style and sustainability, Hunza G and Rose Inc have partnered on a limited edition nine-piece collection designed to inspire your own iconic moments.<\/p>"}},"77cf8c99-bd6c-4798-875e-e7c579111142":{"type":"hunza-about-bottom","settings":{"about_gallery_image_1":"shopify:\/\/shop_images\/hunza-img-11.jpg","about_gallery_image_2":"shopify:\/\/shop_images\/hunza-img-12.jpg"}},"9831751c-8b14-4e6a-9202-fa4f936985ab":{"type":"hunza-community","settings":{"community_title":"Community","community_description":"<p>Snap, share and inspire by tagging @roseinc #roseinc<\/p>"}},"f12814a3-c26c-47d3-b230-ec4b5d880660":{"type":"hunza-shop-all","settings":{"shopall_title":"Shop All","bg_color":"#fafafa","shopall_collection":"hunza-shop-all"}}},"order":["c32995d4-3d31-4552-9fdb-21735e8929dd","0424b625-9c85-4049-ab1b-65afb44663b3","da2b51aa-4563-4421-9406-c8daa7abaa7d","feb2a2b7-8f1a-4d41-ae0b-17d2d798585e","533416d8-c9d2-45ca-b5cf-fa88ad919946","64659452-7388-451e-acff-8fb761f6df85","6ab41c6c-7119-447f-bfcc-1aa1e0a8aecf","9861a174-b773-479a-8ba1-fbc9894c04e3","d3f799f6-fd0d-4f02-8fb2-5534699e21c8","7056d813-74f7-4095-865b-047883a75cf0","77cf8c99-bd6c-4798-875e-e7c579111142","9831751c-8b14-4e6a-9202-fa4f936985ab","f12814a3-c26c-47d3-b230-ec4b5d880660"]}